sommelier/__init__.py
sommelier/adapters/__init__.py
sommelier/adapters/events/__init__.py
sommelier/adapters/events/consumer.py
sommelier/adapters/events/producer.py
sommelier/adapters/rest_mock/__init__.py
sommelier/adapters/rest_mock/registry/__init__.py
sommelier/adapters/rest_mock/registry/application_runner.py
sommelier/adapters/rest_mock/registry/service_mock_registry.py
sommelier/adapters/sockets/__init__.py
sommelier/adapters/sockets/wrapper.py
sommelier/behave_wrapper/__init__.py
sommelier/behave_wrapper/context_manager.py
sommelier/behave_wrapper/provider.py
sommelier/behave_wrapper/test_execution_flow.py
sommelier/behave_wrapper/aliases/__init__.py
sommelier/behave_wrapper/aliases/labels.py
sommelier/behave_wrapper/logging/__init__.py
sommelier/behave_wrapper/logging/beautifier.py
sommelier/behave_wrapper/logging/court.py
sommelier/behave_wrapper/logging/format_str.py
sommelier/behave_wrapper/logging/logger.py
sommelier/behave_wrapper/responses/__init__.py
sommelier/behave_wrapper/responses/response_holder.py
sommelier/behave_wrapper/tables/__init__.py
sommelier/behave_wrapper/tables/builders.py
sommelier/behave_wrapper/tables/carpenter.py
sommelier/behave_wrapper/tables/output.py
sommelier/behave_wrapper/tables/processing.py
sommelier/managers/__init__.py
sommelier/managers/api_mock.py
sommelier/managers/event_managment.py
sommelier/managers/page_navigation.py
sommelier/managers/web_socket.py
sommelier/managers/rest_clients/__init__.py
sommelier/managers/rest_clients/client.py
sommelier/managers/rest_clients/simple.py
sommelier/managers/rest_clients/auth/__init__.py
sommelier/managers/rest_clients/auth/user_registry.py
sommelier/managers/rest_restp/__init__.py
sommelier/managers/rest_restp/json.py
sommelier/managers/rest_restp/list.py
sommelier/managers/rest_restp/response_validation.py
sommelier/steps/__init__.py
sommelier/steps/event_processing.py
sommelier/steps/pagination.py
sommelier/steps/response_processing.py
sommelier/steps/rest_mocking.py
sommelier-1.2.29.dist-info/LICENSE.txt
sommelier-1.2.29.dist-info/METADATA
sommelier-1.2.29.dist-info/WHEEL
sommelier-1.2.29.dist-info/top_level.txt
sommelier-1.2.29.dist-info/RECORD
